Metadata-Version: 2.1
Name: sheepeditor
Version: 0.0.1
Summary: Sheep Own text Editor
Home-page: https://github.com/sleepntsheep/soe
Author: sleepntsheep
Author-email: contact@papangkorn.com
License: UNKNOWN
Platform: UNKNOWN
Requires-Python: >=3.6
